s2/__init__.py
s2/s2.py
s2-0.1.9.dist-info/AUTHORS.rst
s2-0.1.9.dist-info/METADATA
s2-0.1.9.dist-info/WHEEL
s2-0.1.9.dist-info/top_level.txt
s2-0.1.9.dist-info/RECORD
