Metadata-Version: 2.1
Name: s2
Version: 0.1.9
Summary: Python bindings for S2, a hierarchical square geospatial indexing system.
Home-page: https://github.com/JoaoCarabetta/s2
Author: Joao Carabetta
Author-email: joao.carabetta@gmail.com
License: MIT license
Platform: UNKNOWN
Classifier: Development Status :: 2 - Pre-Alpha
Classifier: Intended Audience :: Developers
Classifier: License :: OSI Approved :: MIT License
Classifier: Natural Language :: English
Classifier: Programming Language :: Python :: 3
Requires-Python: >=3
Requires-Dist: s2sphere
Requires-Dist: shapely
